limiter/__init__.py
limiter/base.py
limiter/limiter.py
limiter-0.4.1.dist-info/LICENSE
limiter-0.4.1.dist-info/METADATA
limiter-0.4.1.dist-info/WHEEL
limiter-0.4.1.dist-info/top_level.txt
limiter-0.4.1.dist-info/zip-safe
limiter-0.4.1.dist-info/RECORD
