Metadata-Version: 2.1
Name: limiter
Version: 0.4.1
Summary: ⏲️ Easy rate limiting for Python. Rate limiting async and thread-safe decorators and context managers that use a token bucket algorithm.
Home-page: https://github.com/alexdelorenzo/limiter
Author: Alex DeLorenzo
License: LGPL-3.0
Keywords: rate-limit,rate,limit,token,bucket,token-bucket,token_bucket,tokenbucket,decorator,contextmanager,asynchronous,threadsafe,synchronous
Requires-Python: >=3.10
License-File: LICENSE
Requires-Dist: strenum <0.5.0,>=0.4.7
Requires-Dist: token-bucket <0.4.0,>=0.3.0
